agents/__init__.py
agents/agent_utils.py
agents/create_agents.py
article_assistant/__init__.py
article_assistant/author.py
article_assistant/review.py
article_assistant-0.1.3.dist-info/METADATA
article_assistant-0.1.3.dist-info/WHEEL
article_assistant-0.1.3.dist-info/top_level.txt
article_assistant-0.1.3.dist-info/RECORD
