Metadata-Version: 2.1
Name: article_assistant
Version: 0.1.3
Summary: Draft and review articles through the use of Large Language Models (LLMs)
Author: alkhalifas
Requires-Dist: langchain
Requires-Dist: langchain-openai
Requires-Dist: langchain-experimental
Requires-Dist: langchain-core
Requires-Dist: langchain-community
Requires-Dist: pandas
Requires-Dist: python-docx
Requires-Dist: openai
Requires-Dist: PyPDF2
